rfidpy/SimpleMFRC522.py
rfidpy/__init__.py
rfidpy/mfrc522.py
rfidpy-0.3.dist-info/LICENSE.txt
rfidpy-0.3.dist-info/METADATA
rfidpy-0.3.dist-info/WHEEL
rfidpy-0.3.dist-info/top_level.txt
rfidpy-0.3.dist-info/RECORD
