Metadata-Version: 2.1
Name: rfidpy
Version: 0.3
Summary: Raspberry pi 5 interface with RFID(MFR522)
Home-page: UNKNOWN
Author: M.Karthickraja
Author-email: karthickrajam8100@gmail.com
License: UNKNOWN
Keywords: rfid,raspberry-pi,mfrc522,pi5,python
Platform: UNKNOWN
License-File: LICENSE.txt
